llmfeedback.py
llmfeedback-0.0.5.dist-info/LICENSE
llmfeedback-0.0.5.dist-info/METADATA
llmfeedback-0.0.5.dist-info/WHEEL
llmfeedback-0.0.5.dist-info/top_level.txt
llmfeedback-0.0.5.dist-info/RECORD
